{
  "schemaVersion": 4,
  "author": "11的游戏世界",
  "authorizationId": "auth-eleven-game-world-20260719",
  "pilotRegion": "顺序批次 P25-P35",
  "externalSourceId": "bili-eleven-acshadows-BV1FdQ9YdEcN-p027",
  "page": 27,
  "state": "running",
  "stage": "download",
  "progressPercent": 5.48,
  "processedSeconds": 0.0,
  "durationSeconds": 0.0,
  "sampledFrames": 0,
  "targetFrames": 360,
  "message": "正在下载第 1/1 个分片 · 59.5 MB · 滚动速度 0.19 MB/s",
  "updatedAt": "2026-07-20T15:03:30.549405Z",
  "privacy": "Only public, sanitized task progress is stored. No media URLs, cookies, video files, local paths, or frame pixels are included.",
  "downloadedBytes": 62375132,
  "totalBytes": 107487211,
  "segmentDownloadedBytes": 62375132,
  "segmentTotalBytes": 107487211,
  "segmentIndex": 1,
  "segmentCount": 1,
  "speedBytesPerSecond": 194048.30837675423,
  "averageSpeedBytesPerSecond": 115985.39836613544,
  "etaSeconds": 232.47859967123603,
  "downloadElapsedSeconds": 537.784349398,
  "speedWindowSeconds": 30.228560347000098,
  "stalledSeconds": 0.09340562500005944,
  "heartbeatSequence": 26
}