{
  "schemaVersion": 4,
  "author": "11的游戏世界",
  "authorizationId": "auth-eleven-game-world-20260719",
  "pilotRegion": "顺序批次 P36-P46",
  "externalSourceId": "bili-eleven-acshadows-BV1FdQ9YdEcN-p045",
  "page": 45,
  "state": "running",
  "stage": "download",
  "progressPercent": 5.16,
  "processedSeconds": 0.0,
  "durationSeconds": 0.0,
  "sampledFrames": 0,
  "targetFrames": 360,
  "message": "正在下载第 1/1 个分片 · 51.0 MB · 滚动速度 0.02 MB/s",
  "updatedAt": "2026-07-21T17:43:37.519064Z",
  "privacy": "Only public, sanitized task progress is stored. No media URLs, cookies, video files, local paths, or frame pixels are included.",
  "downloadedBytes": 53474915,
  "totalBytes": 101629162,
  "segmentDownloadedBytes": 53474915,
  "segmentTotalBytes": 101629162,
  "segmentIndex": 1,
  "segmentCount": 1,
  "speedBytesPerSecond": 17282.57792531964,
  "averageSpeedBytesPerSecond": 114185.14253668294,
  "etaSeconds": 2786.288434982386,
  "downloadElapsedSeconds": 468.317627075,
  "speedWindowSeconds": 37.85106613300002,
  "stalledSeconds": 7.3205461840000225,
  "heartbeatSequence": 23
}