{
  "schemaVersion": 4,
  "author": "11的游戏世界",
  "authorizationId": "auth-eleven-game-world-20260719",
  "pilotRegion": "顺序批次 NEXT10 P12-P24",
  "externalSourceId": "bili-eleven-acshadows-BV1FdQ9YdEcN-p023",
  "page": 23,
  "state": "running",
  "stage": "download",
  "progressPercent": 4.55,
  "processedSeconds": 0.0,
  "durationSeconds": 0.0,
  "sampledFrames": 0,
  "targetFrames": 360,
  "message": "正在下载第 1/1 个分片 · 85.9 MB · 滚动速度 0.34 MB/s",
  "updatedAt": "2026-07-20T03:06:38.238778Z",
  "privacy": "Only public, sanitized task progress is stored. No media URLs, cookies, video files, local paths, or frame pixels are included.",
  "downloadedBytes": 90072084,
  "totalBytes": 211556733,
  "segmentDownloadedBytes": 90072084,
  "segmentTotalBytes": 211556733,
  "segmentIndex": 1,
  "segmentCount": 1,
  "speedBytesPerSecond": 359956.8470294183,
  "averageSpeedBytesPerSecond": 609192.17373184,
  "etaSeconds": 337.497813981217,
  "downloadElapsedSeconds": 147.85495921299997,
  "speedWindowSeconds": 7.737916427999949,
  "stalledSeconds": 3.8472040279999646,
  "heartbeatSequence": 8
}