{
  "schemaVersion": 4,
  "author": "11的游戏世界",
  "authorizationId": "auth-eleven-game-world-20260719",
  "pilotRegion": "顺序批次 NEXT10 P12-P24",
  "externalSourceId": "bili-eleven-acshadows-BV1FdQ9YdEcN-p015",
  "page": 15,
  "state": "running",
  "stage": "download",
  "progressPercent": 5.34,
  "processedSeconds": 0.0,
  "durationSeconds": 0.0,
  "sampledFrames": 0,
  "targetFrames": 480,
  "message": "正在下载第 1/1 个分片 · 130.8 MB · 滚动速度 0.72 MB/s",
  "updatedAt": "2026-07-20T02:35:48.067698Z",
  "privacy": "Only public, sanitized task progress is stored. No media URLs, cookies, video files, local paths, or frame pixels are included.",
  "downloadedBytes": 137204562,
  "totalBytes": 246567332,
  "segmentDownloadedBytes": 137204562,
  "segmentTotalBytes": 246567332,
  "segmentIndex": 1,
  "segmentCount": 1,
  "speedBytesPerSecond": 758015.5756084629,
  "averageSpeedBytesPerSecond": 204090.3782618634,
  "etaSeconds": 144.2750960786181,
  "downloadElapsedSeconds": 672.273544537,
  "speedWindowSeconds": 10.449014841999997,
  "stalledSeconds": 0.0010686709999845334,
  "heartbeatSequence": 33
}