{
  "schemaVersion": 4,
  "author": "11的游戏世界",
  "authorizationId": "auth-eleven-game-world-20260719",
  "pilotRegion": "顺序批次 P69-P79",
  "externalSourceId": "bili-eleven-acshadows-BV1FdQ9YdEcN-p070",
  "page": 70,
  "state": "running",
  "stage": "download",
  "progressPercent": 5.94,
  "processedSeconds": 0.0,
  "durationSeconds": 0.0,
  "sampledFrames": 0,
  "targetFrames": 480,
  "message": "正在下载第 1/1 个分片 · 136.2 MB · 滚动速度 0.15 MB/s",
  "updatedAt": "2026-07-22T21:29:50.138910Z",
  "privacy": "Only public, sanitized task progress is stored. No media URLs, cookies, video files, local paths, or frame pixels are included.",
  "downloadedBytes": 142867242,
  "totalBytes": 217338569,
  "segmentDownloadedBytes": 142867242,
  "segmentTotalBytes": 217338569,
  "segmentIndex": 1,
  "segmentCount": 1,
  "speedBytesPerSecond": 158890.873866866,
  "averageSpeedBytesPerSecond": 125954.51554529225,
  "etaSeconds": 468.694804098058,
  "downloadElapsedSeconds": 1134.2764598909998,
  "speedWindowSeconds": 40.4360416909999,
  "stalledSeconds": 1.2089182810000239,
  "heartbeatSequence": 55
}