{
  "schemaVersion": 4,
  "author": "11的游戏世界",
  "authorizationId": "auth-eleven-game-world-20260719",
  "pilotRegion": "顺序批次 P25-P35",
  "externalSourceId": "bili-eleven-acshadows-BV1FdQ9YdEcN-p026",
  "page": 26,
  "state": "running",
  "stage": "download",
  "progressPercent": 5.12,
  "processedSeconds": 0.0,
  "durationSeconds": 0.0,
  "sampledFrames": 0,
  "targetFrames": 360,
  "message": "正在下载第 1/1 个分片 · 45.0 MB · 滚动速度 0.39 MB/s",
  "updatedAt": "2026-07-20T14:44:40.647232Z",
  "privacy": "Only public, sanitized task progress is stored. No media URLs, cookies, video files, local paths, or frame pixels are included.",
  "downloadedBytes": 47147180,
  "totalBytes": 90768933,
  "segmentDownloadedBytes": 47147180,
  "segmentTotalBytes": 90768933,
  "segmentIndex": 1,
  "segmentCount": 1,
  "speedBytesPerSecond": 403707.9015952842,
  "averageSpeedBytesPerSecond": 85023.74197636006,
  "etaSeconds": 108.05275999707992,
  "downloadElapsedSeconds": 554.517819424,
  "speedWindowSeconds": 19.39675931299996,
  "stalledSeconds": 0.04662530799998876,
  "heartbeatSequence": 27
}