{
  "schemaVersion": 4,
  "author": "11的游戏世界",
  "authorizationId": "auth-eleven-game-world-20260719",
  "pilotRegion": "顺序批次 P69-P79",
  "externalSourceId": "bili-eleven-acshadows-BV1FdQ9YdEcN-p075",
  "page": 75,
  "state": "running",
  "stage": "download",
  "progressPercent": 7.87,
  "processedSeconds": 0.0,
  "durationSeconds": 0.0,
  "sampledFrames": 0,
  "targetFrames": 360,
  "message": "正在下载第 1/1 个分片 · 48.9 MB · 滚动速度 0.08 MB/s",
  "updatedAt": "2026-07-22T22:01:16.513199Z",
  "privacy": "Only public, sanitized task progress is stored. No media URLs, cookies, video files, local paths, or frame pixels are included.",
  "downloadedBytes": 51244399,
  "totalBytes": 52393064,
  "segmentDownloadedBytes": 51244399,
  "segmentTotalBytes": 52393064,
  "segmentIndex": 1,
  "segmentCount": 1,
  "speedBytesPerSecond": 79663.43055022617,
  "averageSpeedBytesPerSecond": 484317.83191360655,
  "etaSeconds": 14.41897483031176,
  "downloadElapsedSeconds": 105.807376114,
  "speedWindowSeconds": 31.846958918000013,
  "stalledSeconds": 1.846593791999993,
  "heartbeatSequence": 6
}