{
  "schemaVersion": 4,
  "author": "11的游戏世界",
  "authorizationId": "auth-eleven-game-world-20260719",
  "pilotRegion": "顺序批次 P36-P46",
  "externalSourceId": "bili-eleven-acshadows-BV1FdQ9YdEcN-p036",
  "page": 36,
  "state": "running",
  "stage": "download",
  "progressPercent": 5.08,
  "processedSeconds": 0.0,
  "durationSeconds": 0.0,
  "sampledFrames": 0,
  "targetFrames": 360,
  "message": "正在下载第 1/1 个分片 · 40.1 MB · 滚动速度 0.08 MB/s",
  "updatedAt": "2026-07-22T01:56:48.129795Z",
  "privacy": "Only public, sanitized task progress is stored. No media URLs, cookies, video files, local paths, or frame pixels are included.",
  "downloadedBytes": 42036416,
  "totalBytes": 82016127,
  "segmentDownloadedBytes": 42036416,
  "segmentTotalBytes": 82016127,
  "segmentIndex": 1,
  "segmentCount": 1,
  "speedBytesPerSecond": 86123.1757516772,
  "averageSpeedBytesPerSecond": 141971.00170997265,
  "etaSeconds": 464.2154756958253,
  "downloadElapsedSeconds": 296.09156442999995,
  "speedWindowSeconds": 30.438310908999995,
  "stalledSeconds": 0.26553857400000425,
  "heartbeatSequence": 15
}