{
  "schemaVersion": 1,
  "release": "0.9.4.8",
  "batchId": "reward-batch-011",
  "generatedAt": "2026-07-22T21:47:54.651231Z",
  "recordSchema": "data/rewards/reward-record-schema.json",
  "startIndex": 1001,
  "endIndex": 1100,
  "recordCount": 100,
  "records": [
    {
      "locationId": "location-mapgenie-435753",
      "sourceLocationId": 435753,
      "categoryId": "category-12315-jizo-statue",
      "status": "unresolved",
      "confidence": 0.0,
      "summaryZhCN": "奖励尚未确认",
      "rewards": [],
      "sources": [],
      "conflicts": [],
      "review": {
        "state": "machine_checked",
        "lastReviewedAt": "2026-07-22T21:47:54.651231Z",
        "method": "atlas_reward_builder_v1",
        "reviewer": null,
        "changeReasonZhCN": "从地点原始奖励字段提取，按简体中文术语标准化，并使用独立公开来源进行保守交叉核对。"
      }
    },
    {
      "locationId": "location-mapgenie-435923",
      "sourceLocationId": 435923,
      "categoryId": "category-12315-jizo-statue",
      "status": "unresolved",
      "confidence": 0.0,
      "summaryZhCN": "奖励尚未确认",
      "rewards": [],
      "sources": [],
      "conflicts": [],
      "review": {
        "state": "machine_checked",
        "lastReviewedAt": "2026-07-22T21:47:54.651231Z",
        "method": "atlas_reward_builder_v1",
        "reviewer": null,
        "changeReasonZhCN": "从地点原始奖励字段提取，按简体中文术语标准化，并使用独立公开来源进行保守交叉核对。"
      }
    },
    {
      "locationId": "location-mapgenie-435927",
      "sourceLocationId": 435927,
      "categoryId": "category-12315-jizo-statue",
      "status": "unresolved",
      "confidence": 0.0,
      "summaryZhCN": "奖励尚未确认",
      "rewards": [],
      "sources": [],
      "conflicts": [],
      "review": {
        "state": "machine_checked",
        "lastReviewedAt": "2026-07-22T21:47:54.651231Z",
        "method": "atlas_reward_builder_v1",
        "reviewer": null,
        "changeReasonZhCN": "从地点原始奖励字段提取，按简体中文术语标准化，并使用独立公开来源进行保守交叉核对。"
      }
    },
    {
      "locationId": "location-mapgenie-435934",
      "sourceLocationId": 435934,
      "categoryId": "category-12315-jizo-statue",
      "status": "unresolved",
      "confidence": 0.0,
      "summaryZhCN": "奖励尚未确认",
      "rewards": [],
      "sources": [],
      "conflicts": [],
      "review": {
        "state": "machine_checked",
        "lastReviewedAt": "2026-07-22T21:47:54.651231Z",
        "method": "atlas_reward_builder_v1",
        "reviewer": null,
        "changeReasonZhCN": "从地点原始奖励字段提取，按简体中文术语标准化，并使用独立公开来源进行保守交叉核对。"
      }
    },
    {
      "locationId": "location-mapgenie-435965",
      "sourceLocationId": 435965,
      "categoryId": "category-12315-jizo-statue",
      "status": "unresolved",
      "confidence": 0.0,
      "summaryZhCN": "奖励尚未确认",
      "rewards": [],
      "sources": [],
      "conflicts": [],
      "review": {
        "state": "machine_checked",
        "lastReviewedAt": "2026-07-22T21:47:54.651231Z",
        "method": "atlas_reward_builder_v1",
        "reviewer": null,
        "changeReasonZhCN": "从地点原始奖励字段提取，按简体中文术语标准化，并使用独立公开来源进行保守交叉核对。"
      }
    },
    {
      "locationId": "location-mapgenie-435967",
      "sourceLocationId": 435967,
      "categoryId": "category-12315-jizo-statue",
      "status": "unresolved",
      "confidence": 0.0,
      "summaryZhCN": "奖励尚未确认",
      "rewards": [],
      "sources": [],
      "conflicts": [],
      "review": {
        "state": "machine_checked",
        "lastReviewedAt": "2026-07-22T21:47:54.651231Z",
        "method": "atlas_reward_builder_v1",
        "reviewer": null,
        "changeReasonZhCN": "从地点原始奖励字段提取，按简体中文术语标准化，并使用独立公开来源进行保守交叉核对。"
      }
    },
    {
      "locationId": "location-mapgenie-435979",
      "sourceLocationId": 435979,
      "categoryId": "category-12315-jizo-statue",
      "status": "unresolved",
      "confidence": 0.0,
      "summaryZhCN": "奖励尚未确认",
      "rewards": [],
      "sources": [],
      "conflicts": [],
      "review": {
        "state": "machine_checked",
        "lastReviewedAt": "2026-07-22T21:47:54.651231Z",
        "method": "atlas_reward_builder_v1",
        "reviewer": null,
        "changeReasonZhCN": "从地点原始奖励字段提取，按简体中文术语标准化，并使用独立公开来源进行保守交叉核对。"
      }
    },
    {
      "locationId": "location-mapgenie-436256",
      "sourceLocationId": 436256,
      "categoryId": "category-12315-jizo-statue",
      "status": "unresolved",
      "confidence": 0.0,
      "summaryZhCN": "奖励尚未确认",
      "rewards": [],
      "sources": [],
      "conflicts": [],
      "review": {
        "state": "machine_checked",
        "lastReviewedAt": "2026-07-22T21:47:54.651231Z",
        "method": "atlas_reward_builder_v1",
        "reviewer": null,
        "changeReasonZhCN": "从地点原始奖励字段提取，按简体中文术语标准化，并使用独立公开来源进行保守交叉核对。"
      }
    },
    {
      "locationId": "location-mapgenie-436297",
      "sourceLocationId": 436297,
      "categoryId": "category-12315-jizo-statue",
      "status": "unresolved",
      "confidence": 0.0,
      "summaryZhCN": "奖励尚未确认",
      "rewards": [],
      "sources": [],
      "conflicts": [],
      "review": {
        "state": "machine_checked",
        "lastReviewedAt": "2026-07-22T21:47:54.651231Z",
        "method": "atlas_reward_builder_v1",
        "reviewer": null,
        "changeReasonZhCN": "从地点原始奖励字段提取，按简体中文术语标准化，并使用独立公开来源进行保守交叉核对。"
      }
    },
    {
      "locationId": "location-mapgenie-436366",
      "sourceLocationId": 436366,
      "categoryId": "category-12315-jizo-statue",
      "status": "unresolved",
      "confidence": 0.0,
      "summaryZhCN": "奖励尚未确认",
      "rewards": [],
      "sources": [],
      "conflicts": [],
      "review": {
        "state": "machine_checked",
        "lastReviewedAt": "2026-07-22T21:47:54.651231Z",
        "method": "atlas_reward_builder_v1",
        "reviewer": null,
        "changeReasonZhCN": "从地点原始奖励字段提取，按简体中文术语标准化，并使用独立公开来源进行保守交叉核对。"
      }
    },
    {
      "locationId": "location-mapgenie-436440",
      "sourceLocationId": 436440,
      "categoryId": "category-12315-jizo-statue",
      "status": "unresolved",
      "confidence": 0.0,
      "summaryZhCN": "奖励尚未确认",
      "rewards": [],
      "sources": [],
      "conflicts": [],
      "review": {
        "state": "machine_checked",
        "lastReviewedAt": "2026-07-22T21:47:54.651231Z",
        "method": "atlas_reward_builder_v1",
        "reviewer": null,
        "changeReasonZhCN": "从地点原始奖励字段提取，按简体中文术语标准化，并使用独立公开来源进行保守交叉核对。"
      }
    },
    {
      "locationId": "location-mapgenie-436486",
      "sourceLocationId": 436486,
      "categoryId": "category-12315-jizo-statue",
      "status": "unresolved",
      "confidence": 0.0,
      "summaryZhCN": "奖励尚未确认",
      "rewards": [],
      "sources": [],
      "conflicts": [],
      "review": {
        "state": "machine_checked",
        "lastReviewedAt": "2026-07-22T21:47:54.651231Z",
        "method": "atlas_reward_builder_v1",
        "reviewer": null,
        "changeReasonZhCN": "从地点原始奖励字段提取，按简体中文术语标准化，并使用独立公开来源进行保守交叉核对。"
      }
    },
    {
      "locationId": "location-mapgenie-436681",
      "sourceLocationId": 436681,
      "categoryId": "category-12315-jizo-statue",
      "status": "unresolved",
      "confidence": 0.0,
      "summaryZhCN": "奖励尚未确认",
      "rewards": [],
      "sources": [],
      "conflicts": [],
      "review": {
        "state": "machine_checked",
        "lastReviewedAt": "2026-07-22T21:47:54.651231Z",
        "method": "atlas_reward_builder_v1",
        "reviewer": null,
        "changeReasonZhCN": "从地点原始奖励字段提取，按简体中文术语标准化，并使用独立公开来源进行保守交叉核对。"
      }
    },
    {
      "locationId": "location-mapgenie-436832",
      "sourceLocationId": 436832,
      "categoryId": "category-12315-jizo-statue",
      "status": "unresolved",
      "confidence": 0.0,
      "summaryZhCN": "奖励尚未确认",
      "rewards": [],
      "sources": [],
      "conflicts": [],
      "review": {
        "state": "machine_checked",
        "lastReviewedAt": "2026-07-22T21:47:54.651231Z",
        "method": "atlas_reward_builder_v1",
        "reviewer": null,
        "changeReasonZhCN": "从地点原始奖励字段提取，按简体中文术语标准化，并使用独立公开来源进行保守交叉核对。"
      }
    },
    {
      "locationId": "location-mapgenie-437032",
      "sourceLocationId": 437032,
      "categoryId": "category-12315-jizo-statue",
      "status": "unresolved",
      "confidence": 0.0,
      "summaryZhCN": "奖励尚未确认",
      "rewards": [],
      "sources": [],
      "conflicts": [],
      "review": {
        "state": "machine_checked",
        "lastReviewedAt": "2026-07-22T21:47:54.651231Z",
        "method": "atlas_reward_builder_v1",
        "reviewer": null,
        "changeReasonZhCN": "从地点原始奖励字段提取，按简体中文术语标准化，并使用独立公开来源进行保守交叉核对。"
      }
    },
    {
      "locationId": "location-mapgenie-437054",
      "sourceLocationId": 437054,
      "categoryId": "category-12315-jizo-statue",
      "status": "unresolved",
      "confidence": 0.0,
      "summaryZhCN": "奖励尚未确认",
      "rewards": [],
      "sources": [],
      "conflicts": [],
      "review": {
        "state": "machine_checked",
        "lastReviewedAt": "2026-07-22T21:47:54.651231Z",
        "method": "atlas_reward_builder_v1",
        "reviewer": null,
        "changeReasonZhCN": "从地点原始奖励字段提取，按简体中文术语标准化，并使用独立公开来源进行保守交叉核对。"
      }
    },
    {
      "locationId": "location-mapgenie-437056",
      "sourceLocationId": 437056,
      "categoryId": "category-12315-jizo-statue",
      "status": "unresolved",
      "confidence": 0.0,
      "summaryZhCN": "奖励尚未确认",
      "rewards": [],
      "sources": [],
      "conflicts": [],
      "review": {
        "state": "machine_checked",
        "lastReviewedAt": "2026-07-22T21:47:54.651231Z",
        "method": "atlas_reward_builder_v1",
        "reviewer": null,
        "changeReasonZhCN": "从地点原始奖励字段提取，按简体中文术语标准化，并使用独立公开来源进行保守交叉核对。"
      }
    },
    {
      "locationId": "location-mapgenie-437184",
      "sourceLocationId": 437184,
      "categoryId": "category-12315-jizo-statue",
      "status": "unresolved",
      "confidence": 0.0,
      "summaryZhCN": "奖励尚未确认",
      "rewards": [],
      "sources": [],
      "conflicts": [],
      "review": {
        "state": "machine_checked",
        "lastReviewedAt": "2026-07-22T21:47:54.651231Z",
        "method": "atlas_reward_builder_v1",
        "reviewer": null,
        "changeReasonZhCN": "从地点原始奖励字段提取，按简体中文术语标准化，并使用独立公开来源进行保守交叉核对。"
      }
    },
    {
      "locationId": "location-mapgenie-437259",
      "sourceLocationId": 437259,
      "categoryId": "category-12315-jizo-statue",
      "status": "unresolved",
      "confidence": 0.0,
      "summaryZhCN": "奖励尚未确认",
      "rewards": [],
      "sources": [],
      "conflicts": [],
      "review": {
        "state": "machine_checked",
        "lastReviewedAt": "2026-07-22T21:47:54.651231Z",
        "method": "atlas_reward_builder_v1",
        "reviewer": null,
        "changeReasonZhCN": "从地点原始奖励字段提取，按简体中文术语标准化，并使用独立公开来源进行保守交叉核对。"
      }
    },
    {
      "locationId": "location-mapgenie-437496",
      "sourceLocationId": 437496,
      "categoryId": "category-12315-jizo-statue",
      "status": "unresolved",
      "confidence": 0.0,
      "summaryZhCN": "奖励尚未确认",
      "rewards": [],
      "sources": [],
      "conflicts": [],
      "review": {
        "state": "machine_checked",
        "lastReviewedAt": "2026-07-22T21:47:54.651231Z",
        "method": "atlas_reward_builder_v1",
        "reviewer": null,
        "changeReasonZhCN": "从地点原始奖励字段提取，按简体中文术语标准化，并使用独立公开来源进行保守交叉核对。"
      }
    },
    {
      "locationId": "location-mapgenie-437591",
      "sourceLocationId": 437591,
      "categoryId": "category-12315-jizo-statue",
      "status": "unresolved",
      "confidence": 0.0,
      "summaryZhCN": "奖励尚未确认",
      "rewards": [],
      "sources": [],
      "conflicts": [],
      "review": {
        "state": "machine_checked",
        "lastReviewedAt": "2026-07-22T21:47:54.651231Z",
        "method": "atlas_reward_builder_v1",
        "reviewer": null,
        "changeReasonZhCN": "从地点原始奖励字段提取，按简体中文术语标准化，并使用独立公开来源进行保守交叉核对。"
      }
    },
    {
      "locationId": "location-mapgenie-437619",
      "sourceLocationId": 437619,
      "categoryId": "category-12315-jizo-statue",
      "status": "unresolved",
      "confidence": 0.0,
      "summaryZhCN": "奖励尚未确认",
      "rewards": [],
      "sources": [],
      "conflicts": [],
      "review": {
        "state": "machine_checked",
        "lastReviewedAt": "2026-07-22T21:47:54.651231Z",
        "method": "atlas_reward_builder_v1",
        "reviewer": null,
        "changeReasonZhCN": "从地点原始奖励字段提取，按简体中文术语标准化，并使用独立公开来源进行保守交叉核对。"
      }
    },
    {
      "locationId": "location-mapgenie-437665",
      "sourceLocationId": 437665,
      "categoryId": "category-12315-jizo-statue",
      "status": "unresolved",
      "confidence": 0.0,
      "summaryZhCN": "奖励尚未确认",
      "rewards": [],
      "sources": [],
      "conflicts": [],
      "review": {
        "state": "machine_checked",
        "lastReviewedAt": "2026-07-22T21:47:54.651231Z",
        "method": "atlas_reward_builder_v1",
        "reviewer": null,
        "changeReasonZhCN": "从地点原始奖励字段提取，按简体中文术语标准化，并使用独立公开来源进行保守交叉核对。"
      }
    },
    {
      "locationId": "location-mapgenie-437688",
      "sourceLocationId": 437688,
      "categoryId": "category-12315-jizo-statue",
      "status": "unresolved",
      "confidence": 0.0,
      "summaryZhCN": "奖励尚未确认",
      "rewards": [],
      "sources": [],
      "conflicts": [],
      "review": {
        "state": "machine_checked",
        "lastReviewedAt": "2026-07-22T21:47:54.651231Z",
        "method": "atlas_reward_builder_v1",
        "reviewer": null,
        "changeReasonZhCN": "从地点原始奖励字段提取，按简体中文术语标准化，并使用独立公开来源进行保守交叉核对。"
      }
    },
    {
      "locationId": "location-mapgenie-437801",
      "sourceLocationId": 437801,
      "categoryId": "category-12315-jizo-statue",
      "status": "unresolved",
      "confidence": 0.0,
      "summaryZhCN": "奖励尚未确认",
      "rewards": [],
      "sources": [],
      "conflicts": [],
      "review": {
        "state": "machine_checked",
        "lastReviewedAt": "2026-07-22T21:47:54.651231Z",
        "method": "atlas_reward_builder_v1",
        "reviewer": null,
        "changeReasonZhCN": "从地点原始奖励字段提取，按简体中文术语标准化，并使用独立公开来源进行保守交叉核对。"
      }
    },
    {
      "locationId": "location-mapgenie-437857",
      "sourceLocationId": 437857,
      "categoryId": "category-12315-jizo-statue",
      "status": "unresolved",
      "confidence": 0.0,
      "summaryZhCN": "奖励尚未确认",
      "rewards": [],
      "sources": [],
      "conflicts": [],
      "review": {
        "state": "machine_checked",
        "lastReviewedAt": "2026-07-22T21:47:54.651231Z",
        "method": "atlas_reward_builder_v1",
        "reviewer": null,
        "changeReasonZhCN": "从地点原始奖励字段提取，按简体中文术语标准化，并使用独立公开来源进行保守交叉核对。"
      }
    },
    {
      "locationId": "location-mapgenie-438079",
      "sourceLocationId": 438079,
      "categoryId": "category-12315-jizo-statue",
      "status": "unresolved",
      "confidence": 0.0,
      "summaryZhCN": "奖励尚未确认",
      "rewards": [],
      "sources": [],
      "conflicts": [],
      "review": {
        "state": "machine_checked",
        "lastReviewedAt": "2026-07-22T21:47:54.651231Z",
        "method": "atlas_reward_builder_v1",
        "reviewer": null,
        "changeReasonZhCN": "从地点原始奖励字段提取，按简体中文术语标准化，并使用独立公开来源进行保守交叉核对。"
      }
    },
    {
      "locationId": "location-mapgenie-438080",
      "sourceLocationId": 438080,
      "categoryId": "category-12315-jizo-statue",
      "status": "unresolved",
      "confidence": 0.0,
      "summaryZhCN": "奖励尚未确认",
      "rewards": [],
      "sources": [],
      "conflicts": [],
      "review": {
        "state": "machine_checked",
        "lastReviewedAt": "2026-07-22T21:47:54.651231Z",
        "method": "atlas_reward_builder_v1",
        "reviewer": null,
        "changeReasonZhCN": "从地点原始奖励字段提取，按简体中文术语标准化，并使用独立公开来源进行保守交叉核对。"
      }
    },
    {
      "locationId": "location-mapgenie-438081",
      "sourceLocationId": 438081,
      "categoryId": "category-12315-jizo-statue",
      "status": "unresolved",
      "confidence": 0.0,
      "summaryZhCN": "奖励尚未确认",
      "rewards": [],
      "sources": [],
      "conflicts": [],
      "review": {
        "state": "machine_checked",
        "lastReviewedAt": "2026-07-22T21:47:54.651231Z",
        "method": "atlas_reward_builder_v1",
        "reviewer": null,
        "changeReasonZhCN": "从地点原始奖励字段提取，按简体中文术语标准化，并使用独立公开来源进行保守交叉核对。"
      }
    },
    {
      "locationId": "location-mapgenie-438082",
      "sourceLocationId": 438082,
      "categoryId": "category-12315-jizo-statue",
      "status": "unresolved",
      "confidence": 0.0,
      "summaryZhCN": "奖励尚未确认",
      "rewards": [],
      "sources": [],
      "conflicts": [],
      "review": {
        "state": "machine_checked",
        "lastReviewedAt": "2026-07-22T21:47:54.651231Z",
        "method": "atlas_reward_builder_v1",
        "reviewer": null,
        "changeReasonZhCN": "从地点原始奖励字段提取，按简体中文术语标准化，并使用独立公开来源进行保守交叉核对。"
      }
    },
    {
      "locationId": "location-mapgenie-438097",
      "sourceLocationId": 438097,
      "categoryId": "category-12315-jizo-statue",
      "status": "unresolved",
      "confidence": 0.0,
      "summaryZhCN": "奖励尚未确认",
      "rewards": [],
      "sources": [],
      "conflicts": [],
      "review": {
        "state": "machine_checked",
        "lastReviewedAt": "2026-07-22T21:47:54.651231Z",
        "method": "atlas_reward_builder_v1",
        "reviewer": null,
        "changeReasonZhCN": "从地点原始奖励字段提取，按简体中文术语标准化，并使用独立公开来源进行保守交叉核对。"
      }
    },
    {
      "locationId": "location-mapgenie-438105",
      "sourceLocationId": 438105,
      "categoryId": "category-12315-jizo-statue",
      "status": "unresolved",
      "confidence": 0.0,
      "summaryZhCN": "奖励尚未确认",
      "rewards": [],
      "sources": [],
      "conflicts": [],
      "review": {
        "state": "machine_checked",
        "lastReviewedAt": "2026-07-22T21:47:54.651231Z",
        "method": "atlas_reward_builder_v1",
        "reviewer": null,
        "changeReasonZhCN": "从地点原始奖励字段提取，按简体中文术语标准化，并使用独立公开来源进行保守交叉核对。"
      }
    },
    {
      "locationId": "location-mapgenie-438194",
      "sourceLocationId": 438194,
      "categoryId": "category-12315-jizo-statue",
      "status": "unresolved",
      "confidence": 0.0,
      "summaryZhCN": "奖励尚未确认",
      "rewards": [],
      "sources": [],
      "conflicts": [],
      "review": {
        "state": "machine_checked",
        "lastReviewedAt": "2026-07-22T21:47:54.651231Z",
        "method": "atlas_reward_builder_v1",
        "reviewer": null,
        "changeReasonZhCN": "从地点原始奖励字段提取，按简体中文术语标准化，并使用独立公开来源进行保守交叉核对。"
      }
    },
    {
      "locationId": "location-mapgenie-438224",
      "sourceLocationId": 438224,
      "categoryId": "category-12315-jizo-statue",
      "status": "unresolved",
      "confidence": 0.0,
      "summaryZhCN": "奖励尚未确认",
      "rewards": [],
      "sources": [],
      "conflicts": [],
      "review": {
        "state": "machine_checked",
        "lastReviewedAt": "2026-07-22T21:47:54.651231Z",
        "method": "atlas_reward_builder_v1",
        "reviewer": null,
        "changeReasonZhCN": "从地点原始奖励字段提取，按简体中文术语标准化，并使用独立公开来源进行保守交叉核对。"
      }
    },
    {
      "locationId": "location-mapgenie-438240",
      "sourceLocationId": 438240,
      "categoryId": "category-12315-jizo-statue",
      "status": "unresolved",
      "confidence": 0.0,
      "summaryZhCN": "奖励尚未确认",
      "rewards": [],
      "sources": [],
      "conflicts": [],
      "review": {
        "state": "machine_checked",
        "lastReviewedAt": "2026-07-22T21:47:54.651231Z",
        "method": "atlas_reward_builder_v1",
        "reviewer": null,
        "changeReasonZhCN": "从地点原始奖励字段提取，按简体中文术语标准化，并使用独立公开来源进行保守交叉核对。"
      }
    },
    {
      "locationId": "location-mapgenie-438259",
      "sourceLocationId": 438259,
      "categoryId": "category-12315-jizo-statue",
      "status": "unresolved",
      "confidence": 0.0,
      "summaryZhCN": "奖励尚未确认",
      "rewards": [],
      "sources": [],
      "conflicts": [],
      "review": {
        "state": "machine_checked",
        "lastReviewedAt": "2026-07-22T21:47:54.651231Z",
        "method": "atlas_reward_builder_v1",
        "reviewer": null,
        "changeReasonZhCN": "从地点原始奖励字段提取，按简体中文术语标准化，并使用独立公开来源进行保守交叉核对。"
      }
    },
    {
      "locationId": "location-mapgenie-438269",
      "sourceLocationId": 438269,
      "categoryId": "category-12315-jizo-statue",
      "status": "unresolved",
      "confidence": 0.0,
      "summaryZhCN": "奖励尚未确认",
      "rewards": [],
      "sources": [],
      "conflicts": [],
      "review": {
        "state": "machine_checked",
        "lastReviewedAt": "2026-07-22T21:47:54.651231Z",
        "method": "atlas_reward_builder_v1",
        "reviewer": null,
        "changeReasonZhCN": "从地点原始奖励字段提取，按简体中文术语标准化，并使用独立公开来源进行保守交叉核对。"
      }
    },
    {
      "locationId": "location-mapgenie-438273",
      "sourceLocationId": 438273,
      "categoryId": "category-12315-jizo-statue",
      "status": "unresolved",
      "confidence": 0.0,
      "summaryZhCN": "奖励尚未确认",
      "rewards": [],
      "sources": [],
      "conflicts": [],
      "review": {
        "state": "machine_checked",
        "lastReviewedAt": "2026-07-22T21:47:54.651231Z",
        "method": "atlas_reward_builder_v1",
        "reviewer": null,
        "changeReasonZhCN": "从地点原始奖励字段提取，按简体中文术语标准化，并使用独立公开来源进行保守交叉核对。"
      }
    },
    {
      "locationId": "location-mapgenie-438278",
      "sourceLocationId": 438278,
      "categoryId": "category-12315-jizo-statue",
      "status": "unresolved",
      "confidence": 0.0,
      "summaryZhCN": "奖励尚未确认",
      "rewards": [],
      "sources": [],
      "conflicts": [],
      "review": {
        "state": "machine_checked",
        "lastReviewedAt": "2026-07-22T21:47:54.651231Z",
        "method": "atlas_reward_builder_v1",
        "reviewer": null,
        "changeReasonZhCN": "从地点原始奖励字段提取，按简体中文术语标准化，并使用独立公开来源进行保守交叉核对。"
      }
    },
    {
      "locationId": "location-mapgenie-438291",
      "sourceLocationId": 438291,
      "categoryId": "category-12315-jizo-statue",
      "status": "unresolved",
      "confidence": 0.0,
      "summaryZhCN": "奖励尚未确认",
      "rewards": [],
      "sources": [],
      "conflicts": [],
      "review": {
        "state": "machine_checked",
        "lastReviewedAt": "2026-07-22T21:47:54.651231Z",
        "method": "atlas_reward_builder_v1",
        "reviewer": null,
        "changeReasonZhCN": "从地点原始奖励字段提取，按简体中文术语标准化，并使用独立公开来源进行保守交叉核对。"
      }
    },
    {
      "locationId": "location-mapgenie-438296",
      "sourceLocationId": 438296,
      "categoryId": "category-12315-jizo-statue",
      "status": "unresolved",
      "confidence": 0.0,
      "summaryZhCN": "奖励尚未确认",
      "rewards": [],
      "sources": [],
      "conflicts": [],
      "review": {
        "state": "machine_checked",
        "lastReviewedAt": "2026-07-22T21:47:54.651231Z",
        "method": "atlas_reward_builder_v1",
        "reviewer": null,
        "changeReasonZhCN": "从地点原始奖励字段提取，按简体中文术语标准化，并使用独立公开来源进行保守交叉核对。"
      }
    },
    {
      "locationId": "location-mapgenie-438305",
      "sourceLocationId": 438305,
      "categoryId": "category-12315-jizo-statue",
      "status": "unresolved",
      "confidence": 0.0,
      "summaryZhCN": "奖励尚未确认",
      "rewards": [],
      "sources": [],
      "conflicts": [],
      "review": {
        "state": "machine_checked",
        "lastReviewedAt": "2026-07-22T21:47:54.651231Z",
        "method": "atlas_reward_builder_v1",
        "reviewer": null,
        "changeReasonZhCN": "从地点原始奖励字段提取，按简体中文术语标准化，并使用独立公开来源进行保守交叉核对。"
      }
    },
    {
      "locationId": "location-mapgenie-438374",
      "sourceLocationId": 438374,
      "categoryId": "category-12315-jizo-statue",
      "status": "unresolved",
      "confidence": 0.0,
      "summaryZhCN": "奖励尚未确认",
      "rewards": [],
      "sources": [],
      "conflicts": [],
      "review": {
        "state": "machine_checked",
        "lastReviewedAt": "2026-07-22T21:47:54.651231Z",
        "method": "atlas_reward_builder_v1",
        "reviewer": null,
        "changeReasonZhCN": "从地点原始奖励字段提取，按简体中文术语标准化，并使用独立公开来源进行保守交叉核对。"
      }
    },
    {
      "locationId": "location-mapgenie-438375",
      "sourceLocationId": 438375,
      "categoryId": "category-12315-jizo-statue",
      "status": "unresolved",
      "confidence": 0.0,
      "summaryZhCN": "奖励尚未确认",
      "rewards": [],
      "sources": [],
      "conflicts": [],
      "review": {
        "state": "machine_checked",
        "lastReviewedAt": "2026-07-22T21:47:54.651231Z",
        "method": "atlas_reward_builder_v1",
        "reviewer": null,
        "changeReasonZhCN": "从地点原始奖励字段提取，按简体中文术语标准化，并使用独立公开来源进行保守交叉核对。"
      }
    },
    {
      "locationId": "location-mapgenie-438401",
      "sourceLocationId": 438401,
      "categoryId": "category-12315-jizo-statue",
      "status": "unresolved",
      "confidence": 0.0,
      "summaryZhCN": "奖励尚未确认",
      "rewards": [],
      "sources": [],
      "conflicts": [],
      "review": {
        "state": "machine_checked",
        "lastReviewedAt": "2026-07-22T21:47:54.651231Z",
        "method": "atlas_reward_builder_v1",
        "reviewer": null,
        "changeReasonZhCN": "从地点原始奖励字段提取，按简体中文术语标准化，并使用独立公开来源进行保守交叉核对。"
      }
    },
    {
      "locationId": "location-mapgenie-438422",
      "sourceLocationId": 438422,
      "categoryId": "category-12315-jizo-statue",
      "status": "unresolved",
      "confidence": 0.0,
      "summaryZhCN": "奖励尚未确认",
      "rewards": [],
      "sources": [],
      "conflicts": [],
      "review": {
        "state": "machine_checked",
        "lastReviewedAt": "2026-07-22T21:47:54.651231Z",
        "method": "atlas_reward_builder_v1",
        "reviewer": null,
        "changeReasonZhCN": "从地点原始奖励字段提取，按简体中文术语标准化，并使用独立公开来源进行保守交叉核对。"
      }
    },
    {
      "locationId": "location-mapgenie-438465",
      "sourceLocationId": 438465,
      "categoryId": "category-12315-jizo-statue",
      "status": "unresolved",
      "confidence": 0.0,
      "summaryZhCN": "奖励尚未确认",
      "rewards": [],
      "sources": [],
      "conflicts": [],
      "review": {
        "state": "machine_checked",
        "lastReviewedAt": "2026-07-22T21:47:54.651231Z",
        "method": "atlas_reward_builder_v1",
        "reviewer": null,
        "changeReasonZhCN": "从地点原始奖励字段提取，按简体中文术语标准化，并使用独立公开来源进行保守交叉核对。"
      }
    },
    {
      "locationId": "location-mapgenie-438473",
      "sourceLocationId": 438473,
      "categoryId": "category-12315-jizo-statue",
      "status": "unresolved",
      "confidence": 0.0,
      "summaryZhCN": "奖励尚未确认",
      "rewards": [],
      "sources": [],
      "conflicts": [],
      "review": {
        "state": "machine_checked",
        "lastReviewedAt": "2026-07-22T21:47:54.651231Z",
        "method": "atlas_reward_builder_v1",
        "reviewer": null,
        "changeReasonZhCN": "从地点原始奖励字段提取，按简体中文术语标准化，并使用独立公开来源进行保守交叉核对。"
      }
    },
    {
      "locationId": "location-mapgenie-438481",
      "sourceLocationId": 438481,
      "categoryId": "category-12315-jizo-statue",
      "status": "unresolved",
      "confidence": 0.0,
      "summaryZhCN": "奖励尚未确认",
      "rewards": [],
      "sources": [],
      "conflicts": [],
      "review": {
        "state": "machine_checked",
        "lastReviewedAt": "2026-07-22T21:47:54.651231Z",
        "method": "atlas_reward_builder_v1",
        "reviewer": null,
        "changeReasonZhCN": "从地点原始奖励字段提取，按简体中文术语标准化，并使用独立公开来源进行保守交叉核对。"
      }
    },
    {
      "locationId": "location-mapgenie-438497",
      "sourceLocationId": 438497,
      "categoryId": "category-12315-jizo-statue",
      "status": "unresolved",
      "confidence": 0.0,
      "summaryZhCN": "奖励尚未确认",
      "rewards": [],
      "sources": [],
      "conflicts": [],
      "review": {
        "state": "machine_checked",
        "lastReviewedAt": "2026-07-22T21:47:54.651231Z",
        "method": "atlas_reward_builder_v1",
        "reviewer": null,
        "changeReasonZhCN": "从地点原始奖励字段提取，按简体中文术语标准化，并使用独立公开来源进行保守交叉核对。"
      }
    },
    {
      "locationId": "location-mapgenie-438747",
      "sourceLocationId": 438747,
      "categoryId": "category-12315-jizo-statue",
      "status": "unresolved",
      "confidence": 0.0,
      "summaryZhCN": "奖励尚未确认",
      "rewards": [],
      "sources": [],
      "conflicts": [],
      "review": {
        "state": "machine_checked",
        "lastReviewedAt": "2026-07-22T21:47:54.651231Z",
        "method": "atlas_reward_builder_v1",
        "reviewer": null,
        "changeReasonZhCN": "从地点原始奖励字段提取，按简体中文术语标准化，并使用独立公开来源进行保守交叉核对。"
      }
    },
    {
      "locationId": "location-mapgenie-438755",
      "sourceLocationId": 438755,
      "categoryId": "category-12315-jizo-statue",
      "status": "unresolved",
      "confidence": 0.0,
      "summaryZhCN": "奖励尚未确认",
      "rewards": [],
      "sources": [],
      "conflicts": [],
      "review": {
        "state": "machine_checked",
        "lastReviewedAt": "2026-07-22T21:47:54.651231Z",
        "method": "atlas_reward_builder_v1",
        "reviewer": null,
        "changeReasonZhCN": "从地点原始奖励字段提取，按简体中文术语标准化，并使用独立公开来源进行保守交叉核对。"
      }
    },
    {
      "locationId": "location-mapgenie-438757",
      "sourceLocationId": 438757,
      "categoryId": "category-12315-jizo-statue",
      "status": "unresolved",
      "confidence": 0.0,
      "summaryZhCN": "奖励尚未确认",
      "rewards": [],
      "sources": [],
      "conflicts": [],
      "review": {
        "state": "machine_checked",
        "lastReviewedAt": "2026-07-22T21:47:54.651231Z",
        "method": "atlas_reward_builder_v1",
        "reviewer": null,
        "changeReasonZhCN": "从地点原始奖励字段提取，按简体中文术语标准化，并使用独立公开来源进行保守交叉核对。"
      }
    },
    {
      "locationId": "location-mapgenie-438815",
      "sourceLocationId": 438815,
      "categoryId": "category-12315-jizo-statue",
      "status": "unresolved",
      "confidence": 0.0,
      "summaryZhCN": "奖励尚未确认",
      "rewards": [],
      "sources": [],
      "conflicts": [],
      "review": {
        "state": "machine_checked",
        "lastReviewedAt": "2026-07-22T21:47:54.651231Z",
        "method": "atlas_reward_builder_v1",
        "reviewer": null,
        "changeReasonZhCN": "从地点原始奖励字段提取，按简体中文术语标准化，并使用独立公开来源进行保守交叉核对。"
      }
    },
    {
      "locationId": "location-mapgenie-439244",
      "sourceLocationId": 439244,
      "categoryId": "category-12315-jizo-statue",
      "status": "unresolved",
      "confidence": 0.0,
      "summaryZhCN": "奖励尚未确认",
      "rewards": [],
      "sources": [],
      "conflicts": [],
      "review": {
        "state": "machine_checked",
        "lastReviewedAt": "2026-07-22T21:47:54.651231Z",
        "method": "atlas_reward_builder_v1",
        "reviewer": null,
        "changeReasonZhCN": "从地点原始奖励字段提取，按简体中文术语标准化，并使用独立公开来源进行保守交叉核对。"
      }
    },
    {
      "locationId": "location-mapgenie-439374",
      "sourceLocationId": 439374,
      "categoryId": "category-12315-jizo-statue",
      "status": "unresolved",
      "confidence": 0.0,
      "summaryZhCN": "奖励尚未确认",
      "rewards": [],
      "sources": [],
      "conflicts": [],
      "review": {
        "state": "machine_checked",
        "lastReviewedAt": "2026-07-22T21:47:54.651231Z",
        "method": "atlas_reward_builder_v1",
        "reviewer": null,
        "changeReasonZhCN": "从地点原始奖励字段提取，按简体中文术语标准化，并使用独立公开来源进行保守交叉核对。"
      }
    },
    {
      "locationId": "location-mapgenie-439376",
      "sourceLocationId": 439376,
      "categoryId": "category-12315-jizo-statue",
      "status": "unresolved",
      "confidence": 0.0,
      "summaryZhCN": "奖励尚未确认",
      "rewards": [],
      "sources": [],
      "conflicts": [],
      "review": {
        "state": "machine_checked",
        "lastReviewedAt": "2026-07-22T21:47:54.651231Z",
        "method": "atlas_reward_builder_v1",
        "reviewer": null,
        "changeReasonZhCN": "从地点原始奖励字段提取，按简体中文术语标准化，并使用独立公开来源进行保守交叉核对。"
      }
    },
    {
      "locationId": "location-mapgenie-439378",
      "sourceLocationId": 439378,
      "categoryId": "category-12315-jizo-statue",
      "status": "unresolved",
      "confidence": 0.0,
      "summaryZhCN": "奖励尚未确认",
      "rewards": [],
      "sources": [],
      "conflicts": [],
      "review": {
        "state": "machine_checked",
        "lastReviewedAt": "2026-07-22T21:47:54.651231Z",
        "method": "atlas_reward_builder_v1",
        "reviewer": null,
        "changeReasonZhCN": "从地点原始奖励字段提取，按简体中文术语标准化，并使用独立公开来源进行保守交叉核对。"
      }
    },
    {
      "locationId": "location-mapgenie-439418",
      "sourceLocationId": 439418,
      "categoryId": "category-12315-jizo-statue",
      "status": "unresolved",
      "confidence": 0.0,
      "summaryZhCN": "奖励尚未确认",
      "rewards": [],
      "sources": [],
      "conflicts": [],
      "review": {
        "state": "machine_checked",
        "lastReviewedAt": "2026-07-22T21:47:54.651231Z",
        "method": "atlas_reward_builder_v1",
        "reviewer": null,
        "changeReasonZhCN": "从地点原始奖励字段提取，按简体中文术语标准化，并使用独立公开来源进行保守交叉核对。"
      }
    },
    {
      "locationId": "location-mapgenie-439466",
      "sourceLocationId": 439466,
      "categoryId": "category-12315-jizo-statue",
      "status": "unresolved",
      "confidence": 0.0,
      "summaryZhCN": "奖励尚未确认",
      "rewards": [],
      "sources": [],
      "conflicts": [],
      "review": {
        "state": "machine_checked",
        "lastReviewedAt": "2026-07-22T21:47:54.651231Z",
        "method": "atlas_reward_builder_v1",
        "reviewer": null,
        "changeReasonZhCN": "从地点原始奖励字段提取，按简体中文术语标准化，并使用独立公开来源进行保守交叉核对。"
      }
    },
    {
      "locationId": "location-mapgenie-439669",
      "sourceLocationId": 439669,
      "categoryId": "category-12315-jizo-statue",
      "status": "unresolved",
      "confidence": 0.0,
      "summaryZhCN": "奖励尚未确认",
      "rewards": [],
      "sources": [],
      "conflicts": [],
      "review": {
        "state": "machine_checked",
        "lastReviewedAt": "2026-07-22T21:47:54.651231Z",
        "method": "atlas_reward_builder_v1",
        "reviewer": null,
        "changeReasonZhCN": "从地点原始奖励字段提取，按简体中文术语标准化，并使用独立公开来源进行保守交叉核对。"
      }
    },
    {
      "locationId": "location-mapgenie-435724",
      "sourceLocationId": 435724,
      "categoryId": "category-12332-kamon-crest",
      "status": "unresolved",
      "confidence": 0.0,
      "summaryZhCN": "奖励尚未确认",
      "rewards": [],
      "sources": [],
      "conflicts": [],
      "review": {
        "state": "machine_checked",
        "lastReviewedAt": "2026-07-22T21:47:54.651231Z",
        "method": "atlas_reward_builder_v1",
        "reviewer": null,
        "changeReasonZhCN": "从地点原始奖励字段提取，按简体中文术语标准化，并使用独立公开来源进行保守交叉核对。"
      }
    },
    {
      "locationId": "location-mapgenie-435931",
      "sourceLocationId": 435931,
      "categoryId": "category-12332-kamon-crest",
      "status": "unresolved",
      "confidence": 0.0,
      "summaryZhCN": "奖励尚未确认",
      "rewards": [],
      "sources": [],
      "conflicts": [],
      "review": {
        "state": "machine_checked",
        "lastReviewedAt": "2026-07-22T21:47:54.651231Z",
        "method": "atlas_reward_builder_v1",
        "reviewer": null,
        "changeReasonZhCN": "从地点原始奖励字段提取，按简体中文术语标准化，并使用独立公开来源进行保守交叉核对。"
      }
    },
    {
      "locationId": "location-mapgenie-435943",
      "sourceLocationId": 435943,
      "categoryId": "category-12332-kamon-crest",
      "status": "unresolved",
      "confidence": 0.0,
      "summaryZhCN": "奖励尚未确认",
      "rewards": [],
      "sources": [],
      "conflicts": [],
      "review": {
        "state": "machine_checked",
        "lastReviewedAt": "2026-07-22T21:47:54.651231Z",
        "method": "atlas_reward_builder_v1",
        "reviewer": null,
        "changeReasonZhCN": "从地点原始奖励字段提取，按简体中文术语标准化，并使用独立公开来源进行保守交叉核对。"
      }
    },
    {
      "locationId": "location-mapgenie-436812",
      "sourceLocationId": 436812,
      "categoryId": "category-12332-kamon-crest",
      "status": "unresolved",
      "confidence": 0.0,
      "summaryZhCN": "奖励尚未确认",
      "rewards": [],
      "sources": [],
      "conflicts": [],
      "review": {
        "state": "machine_checked",
        "lastReviewedAt": "2026-07-22T21:47:54.651231Z",
        "method": "atlas_reward_builder_v1",
        "reviewer": null,
        "changeReasonZhCN": "从地点原始奖励字段提取，按简体中文术语标准化，并使用独立公开来源进行保守交叉核对。"
      }
    },
    {
      "locationId": "location-mapgenie-437323",
      "sourceLocationId": 437323,
      "categoryId": "category-12332-kamon-crest",
      "status": "unresolved",
      "confidence": 0.0,
      "summaryZhCN": "奖励尚未确认",
      "rewards": [],
      "sources": [],
      "conflicts": [],
      "review": {
        "state": "machine_checked",
        "lastReviewedAt": "2026-07-22T21:47:54.651231Z",
        "method": "atlas_reward_builder_v1",
        "reviewer": null,
        "changeReasonZhCN": "从地点原始奖励字段提取，按简体中文术语标准化，并使用独立公开来源进行保守交叉核对。"
      }
    },
    {
      "locationId": "location-mapgenie-437584",
      "sourceLocationId": 437584,
      "categoryId": "category-12332-kamon-crest",
      "status": "unresolved",
      "confidence": 0.0,
      "summaryZhCN": "奖励尚未确认",
      "rewards": [],
      "sources": [],
      "conflicts": [],
      "review": {
        "state": "machine_checked",
        "lastReviewedAt": "2026-07-22T21:47:54.651231Z",
        "method": "atlas_reward_builder_v1",
        "reviewer": null,
        "changeReasonZhCN": "从地点原始奖励字段提取，按简体中文术语标准化，并使用独立公开来源进行保守交叉核对。"
      }
    },
    {
      "locationId": "location-mapgenie-437925",
      "sourceLocationId": 437925,
      "categoryId": "category-12332-kamon-crest",
      "status": "unresolved",
      "confidence": 0.0,
      "summaryZhCN": "奖励尚未确认",
      "rewards": [],
      "sources": [],
      "conflicts": [],
      "review": {
        "state": "machine_checked",
        "lastReviewedAt": "2026-07-22T21:47:54.651231Z",
        "method": "atlas_reward_builder_v1",
        "reviewer": null,
        "changeReasonZhCN": "从地点原始奖励字段提取，按简体中文术语标准化，并使用独立公开来源进行保守交叉核对。"
      }
    },
    {
      "locationId": "location-mapgenie-438466",
      "sourceLocationId": 438466,
      "categoryId": "category-12332-kamon-crest",
      "status": "unresolved",
      "confidence": 0.0,
      "summaryZhCN": "奖励尚未确认",
      "rewards": [],
      "sources": [],
      "conflicts": [],
      "review": {
        "state": "machine_checked",
        "lastReviewedAt": "2026-07-22T21:47:54.651231Z",
        "method": "atlas_reward_builder_v1",
        "reviewer": null,
        "changeReasonZhCN": "从地点原始奖励字段提取，按简体中文术语标准化，并使用独立公开来源进行保守交叉核对。"
      }
    },
    {
      "locationId": "location-mapgenie-439467",
      "sourceLocationId": 439467,
      "categoryId": "category-12332-kamon-crest",
      "status": "unresolved",
      "confidence": 0.0,
      "summaryZhCN": "奖励尚未确认",
      "rewards": [],
      "sources": [],
      "conflicts": [],
      "review": {
        "state": "machine_checked",
        "lastReviewedAt": "2026-07-22T21:47:54.651231Z",
        "method": "atlas_reward_builder_v1",
        "reviewer": null,
        "changeReasonZhCN": "从地点原始奖励字段提取，按简体中文术语标准化，并使用独立公开来源进行保守交叉核对。"
      }
    },
    {
      "locationId": "location-mapgenie-434490",
      "sourceLocationId": 434490,
      "categoryId": "category-12326-kano-painting",
      "status": "unresolved",
      "confidence": 0.0,
      "summaryZhCN": "奖励尚未确认",
      "rewards": [],
      "sources": [],
      "conflicts": [],
      "review": {
        "state": "machine_checked",
        "lastReviewedAt": "2026-07-22T21:47:54.651231Z",
        "method": "atlas_reward_builder_v1",
        "reviewer": null,
        "changeReasonZhCN": "从地点原始奖励字段提取，按简体中文术语标准化，并使用独立公开来源进行保守交叉核对。"
      }
    },
    {
      "locationId": "location-mapgenie-434641",
      "sourceLocationId": 434641,
      "categoryId": "category-12326-kano-painting",
      "status": "unresolved",
      "confidence": 0.0,
      "summaryZhCN": "奖励尚未确认",
      "rewards": [],
      "sources": [],
      "conflicts": [],
      "review": {
        "state": "machine_checked",
        "lastReviewedAt": "2026-07-22T21:47:54.651231Z",
        "method": "atlas_reward_builder_v1",
        "reviewer": null,
        "changeReasonZhCN": "从地点原始奖励字段提取，按简体中文术语标准化，并使用独立公开来源进行保守交叉核对。"
      }
    },
    {
      "locationId": "location-mapgenie-434763",
      "sourceLocationId": 434763,
      "categoryId": "category-12326-kano-painting",
      "status": "unresolved",
      "confidence": 0.0,
      "summaryZhCN": "奖励尚未确认",
      "rewards": [],
      "sources": [],
      "conflicts": [],
      "review": {
        "state": "machine_checked",
        "lastReviewedAt": "2026-07-22T21:47:54.651231Z",
        "method": "atlas_reward_builder_v1",
        "reviewer": null,
        "changeReasonZhCN": "从地点原始奖励字段提取，按简体中文术语标准化，并使用独立公开来源进行保守交叉核对。"
      }
    },
    {
      "locationId": "location-mapgenie-434798",
      "sourceLocationId": 434798,
      "categoryId": "category-12326-kano-painting",
      "status": "unresolved",
      "confidence": 0.0,
      "summaryZhCN": "奖励尚未确认",
      "rewards": [],
      "sources": [],
      "conflicts": [],
      "review": {
        "state": "machine_checked",
        "lastReviewedAt": "2026-07-22T21:47:54.651231Z",
        "method": "atlas_reward_builder_v1",
        "reviewer": null,
        "changeReasonZhCN": "从地点原始奖励字段提取，按简体中文术语标准化，并使用独立公开来源进行保守交叉核对。"
      }
    },
    {
      "locationId": "location-mapgenie-435861",
      "sourceLocationId": 435861,
      "categoryId": "category-12326-kano-painting",
      "status": "unresolved",
      "confidence": 0.0,
      "summaryZhCN": "奖励尚未确认",
      "rewards": [],
      "sources": [],
      "conflicts": [],
      "review": {
        "state": "machine_checked",
        "lastReviewedAt": "2026-07-22T21:47:54.651231Z",
        "method": "atlas_reward_builder_v1",
        "reviewer": null,
        "changeReasonZhCN": "从地点原始奖励字段提取，按简体中文术语标准化，并使用独立公开来源进行保守交叉核对。"
      }
    },
    {
      "locationId": "location-mapgenie-436180",
      "sourceLocationId": 436180,
      "categoryId": "category-12326-kano-painting",
      "status": "unresolved",
      "confidence": 0.0,
      "summaryZhCN": "奖励尚未确认",
      "rewards": [],
      "sources": [],
      "conflicts": [],
      "review": {
        "state": "machine_checked",
        "lastReviewedAt": "2026-07-22T21:47:54.651231Z",
        "method": "atlas_reward_builder_v1",
        "reviewer": null,
        "changeReasonZhCN": "从地点原始奖励字段提取，按简体中文术语标准化，并使用独立公开来源进行保守交叉核对。"
      }
    },
    {
      "locationId": "location-mapgenie-436708",
      "sourceLocationId": 436708,
      "categoryId": "category-12326-kano-painting",
      "status": "unresolved",
      "confidence": 0.0,
      "summaryZhCN": "奖励尚未确认",
      "rewards": [],
      "sources": [],
      "conflicts": [],
      "review": {
        "state": "machine_checked",
        "lastReviewedAt": "2026-07-22T21:47:54.651231Z",
        "method": "atlas_reward_builder_v1",
        "reviewer": null,
        "changeReasonZhCN": "从地点原始奖励字段提取，按简体中文术语标准化，并使用独立公开来源进行保守交叉核对。"
      }
    },
    {
      "locationId": "location-mapgenie-437698",
      "sourceLocationId": 437698,
      "categoryId": "category-12326-kano-painting",
      "status": "unresolved",
      "confidence": 0.0,
      "summaryZhCN": "奖励尚未确认",
      "rewards": [],
      "sources": [],
      "conflicts": [],
      "review": {
        "state": "machine_checked",
        "lastReviewedAt": "2026-07-22T21:47:54.651231Z",
        "method": "atlas_reward_builder_v1",
        "reviewer": null,
        "changeReasonZhCN": "从地点原始奖励字段提取，按简体中文术语标准化，并使用独立公开来源进行保守交叉核对。"
      }
    },
    {
      "locationId": "location-mapgenie-437815",
      "sourceLocationId": 437815,
      "categoryId": "category-12326-kano-painting",
      "status": "unresolved",
      "confidence": 0.0,
      "summaryZhCN": "奖励尚未确认",
      "rewards": [],
      "sources": [],
      "conflicts": [],
      "review": {
        "state": "machine_checked",
        "lastReviewedAt": "2026-07-22T21:47:54.651231Z",
        "method": "atlas_reward_builder_v1",
        "reviewer": null,
        "changeReasonZhCN": "从地点原始奖励字段提取，按简体中文术语标准化，并使用独立公开来源进行保守交叉核对。"
      }
    },
    {
      "locationId": "location-mapgenie-437926",
      "sourceLocationId": 437926,
      "categoryId": "category-12326-kano-painting",
      "status": "unresolved",
      "confidence": 0.0,
      "summaryZhCN": "奖励尚未确认",
      "rewards": [],
      "sources": [],
      "conflicts": [],
      "review": {
        "state": "machine_checked",
        "lastReviewedAt": "2026-07-22T21:47:54.651231Z",
        "method": "atlas_reward_builder_v1",
        "reviewer": null,
        "changeReasonZhCN": "从地点原始奖励字段提取，按简体中文术语标准化，并使用独立公开来源进行保守交叉核对。"
      }
    },
    {
      "locationId": "location-mapgenie-434425",
      "sourceLocationId": 434425,
      "categoryId": "category-12342-legendary-chest",
      "status": "unresolved",
      "confidence": 0.0,
      "summaryZhCN": "奖励尚未确认",
      "rewards": [],
      "sources": [],
      "conflicts": [],
      "review": {
        "state": "machine_checked",
        "lastReviewedAt": "2026-07-22T21:47:54.651231Z",
        "method": "atlas_reward_builder_v1",
        "reviewer": null,
        "changeReasonZhCN": "从地点原始奖励字段提取，按简体中文术语标准化，并使用独立公开来源进行保守交叉核对。"
      }
    },
    {
      "locationId": "location-mapgenie-434483",
      "sourceLocationId": 434483,
      "categoryId": "category-12342-legendary-chest",
      "status": "unresolved",
      "confidence": 0.0,
      "summaryZhCN": "奖励尚未确认",
      "rewards": [],
      "sources": [],
      "conflicts": [],
      "review": {
        "state": "machine_checked",
        "lastReviewedAt": "2026-07-22T21:47:54.651231Z",
        "method": "atlas_reward_builder_v1",
        "reviewer": null,
        "changeReasonZhCN": "从地点原始奖励字段提取，按简体中文术语标准化，并使用独立公开来源进行保守交叉核对。"
      }
    },
    {
      "locationId": "location-mapgenie-434597",
      "sourceLocationId": 434597,
      "categoryId": "category-12342-legendary-chest",
      "status": "unresolved",
      "confidence": 0.0,
      "summaryZhCN": "奖励尚未确认",
      "rewards": [],
      "sources": [],
      "conflicts": [],
      "review": {
        "state": "machine_checked",
        "lastReviewedAt": "2026-07-22T21:47:54.651231Z",
        "method": "atlas_reward_builder_v1",
        "reviewer": null,
        "changeReasonZhCN": "从地点原始奖励字段提取，按简体中文术语标准化，并使用独立公开来源进行保守交叉核对。"
      }
    },
    {
      "locationId": "location-mapgenie-434645",
      "sourceLocationId": 434645,
      "categoryId": "category-12342-legendary-chest",
      "status": "unresolved",
      "confidence": 0.0,
      "summaryZhCN": "奖励尚未确认",
      "rewards": [],
      "sources": [],
      "conflicts": [],
      "review": {
        "state": "machine_checked",
        "lastReviewedAt": "2026-07-22T21:47:54.651231Z",
        "method": "atlas_reward_builder_v1",
        "reviewer": null,
        "changeReasonZhCN": "从地点原始奖励字段提取，按简体中文术语标准化，并使用独立公开来源进行保守交叉核对。"
      }
    },
    {
      "locationId": "location-mapgenie-434731",
      "sourceLocationId": 434731,
      "categoryId": "category-12342-legendary-chest",
      "status": "unresolved",
      "confidence": 0.0,
      "summaryZhCN": "奖励尚未确认",
      "rewards": [],
      "sources": [],
      "conflicts": [],
      "review": {
        "state": "machine_checked",
        "lastReviewedAt": "2026-07-22T21:47:54.651231Z",
        "method": "atlas_reward_builder_v1",
        "reviewer": null,
        "changeReasonZhCN": "从地点原始奖励字段提取，按简体中文术语标准化，并使用独立公开来源进行保守交叉核对。"
      }
    },
    {
      "locationId": "location-mapgenie-434767",
      "sourceLocationId": 434767,
      "categoryId": "category-12342-legendary-chest",
      "status": "unresolved",
      "confidence": 0.0,
      "summaryZhCN": "奖励尚未确认",
      "rewards": [],
      "sources": [],
      "conflicts": [],
      "review": {
        "state": "machine_checked",
        "lastReviewedAt": "2026-07-22T21:47:54.651231Z",
        "method": "atlas_reward_builder_v1",
        "reviewer": null,
        "changeReasonZhCN": "从地点原始奖励字段提取，按简体中文术语标准化，并使用独立公开来源进行保守交叉核对。"
      }
    },
    {
      "locationId": "location-mapgenie-434804",
      "sourceLocationId": 434804,
      "categoryId": "category-12342-legendary-chest",
      "status": "unresolved",
      "confidence": 0.0,
      "summaryZhCN": "奖励尚未确认",
      "rewards": [],
      "sources": [],
      "conflicts": [],
      "review": {
        "state": "machine_checked",
        "lastReviewedAt": "2026-07-22T21:47:54.651231Z",
        "method": "atlas_reward_builder_v1",
        "reviewer": null,
        "changeReasonZhCN": "从地点原始奖励字段提取，按简体中文术语标准化，并使用独立公开来源进行保守交叉核对。"
      }
    },
    {
      "locationId": "location-mapgenie-434980",
      "sourceLocationId": 434980,
      "categoryId": "category-12342-legendary-chest",
      "status": "unresolved",
      "confidence": 0.0,
      "summaryZhCN": "奖励尚未确认",
      "rewards": [],
      "sources": [],
      "conflicts": [],
      "review": {
        "state": "machine_checked",
        "lastReviewedAt": "2026-07-22T21:47:54.651231Z",
        "method": "atlas_reward_builder_v1",
        "reviewer": null,
        "changeReasonZhCN": "从地点原始奖励字段提取，按简体中文术语标准化，并使用独立公开来源进行保守交叉核对。"
      }
    },
    {
      "locationId": "location-mapgenie-435026",
      "sourceLocationId": 435026,
      "categoryId": "category-12342-legendary-chest",
      "status": "unresolved",
      "confidence": 0.0,
      "summaryZhCN": "奖励尚未确认",
      "rewards": [],
      "sources": [],
      "conflicts": [],
      "review": {
        "state": "machine_checked",
        "lastReviewedAt": "2026-07-22T21:47:54.651231Z",
        "method": "atlas_reward_builder_v1",
        "reviewer": null,
        "changeReasonZhCN": "从地点原始奖励字段提取，按简体中文术语标准化，并使用独立公开来源进行保守交叉核对。"
      }
    },
    {
      "locationId": "location-mapgenie-435068",
      "sourceLocationId": 435068,
      "categoryId": "category-12342-legendary-chest",
      "status": "unresolved",
      "confidence": 0.0,
      "summaryZhCN": "奖励尚未确认",
      "rewards": [],
      "sources": [],
      "conflicts": [],
      "review": {
        "state": "machine_checked",
        "lastReviewedAt": "2026-07-22T21:47:54.651231Z",
        "method": "atlas_reward_builder_v1",
        "reviewer": null,
        "changeReasonZhCN": "从地点原始奖励字段提取，按简体中文术语标准化，并使用独立公开来源进行保守交叉核对。"
      }
    },
    {
      "locationId": "location-mapgenie-435077",
      "sourceLocationId": 435077,
      "categoryId": "category-12342-legendary-chest",
      "status": "unresolved",
      "confidence": 0.0,
      "summaryZhCN": "奖励尚未确认",
      "rewards": [],
      "sources": [],
      "conflicts": [],
      "review": {
        "state": "machine_checked",
        "lastReviewedAt": "2026-07-22T21:47:54.651231Z",
        "method": "atlas_reward_builder_v1",
        "reviewer": null,
        "changeReasonZhCN": "从地点原始奖励字段提取，按简体中文术语标准化，并使用独立公开来源进行保守交叉核对。"
      }
    },
    {
      "locationId": "location-mapgenie-435100",
      "sourceLocationId": 435100,
      "categoryId": "category-12342-legendary-chest",
      "status": "unresolved",
      "confidence": 0.0,
      "summaryZhCN": "奖励尚未确认",
      "rewards": [],
      "sources": [],
      "conflicts": [],
      "review": {
        "state": "machine_checked",
        "lastReviewedAt": "2026-07-22T21:47:54.651231Z",
        "method": "atlas_reward_builder_v1",
        "reviewer": null,
        "changeReasonZhCN": "从地点原始奖励字段提取，按简体中文术语标准化，并使用独立公开来源进行保守交叉核对。"
      }
    },
    {
      "locationId": "location-mapgenie-435116",
      "sourceLocationId": 435116,
      "categoryId": "category-12342-legendary-chest",
      "status": "unresolved",
      "confidence": 0.0,
      "summaryZhCN": "奖励尚未确认",
      "rewards": [],
      "sources": [],
      "conflicts": [],
      "review": {
        "state": "machine_checked",
        "lastReviewedAt": "2026-07-22T21:47:54.651231Z",
        "method": "atlas_reward_builder_v1",
        "reviewer": null,
        "changeReasonZhCN": "从地点原始奖励字段提取，按简体中文术语标准化，并使用独立公开来源进行保守交叉核对。"
      }
    },
    {
      "locationId": "location-mapgenie-435686",
      "sourceLocationId": 435686,
      "categoryId": "category-12342-legendary-chest",
      "status": "unresolved",
      "confidence": 0.0,
      "summaryZhCN": "奖励尚未确认",
      "rewards": [],
      "sources": [],
      "conflicts": [],
      "review": {
        "state": "machine_checked",
        "lastReviewedAt": "2026-07-22T21:47:54.651231Z",
        "method": "atlas_reward_builder_v1",
        "reviewer": null,
        "changeReasonZhCN": "从地点原始奖励字段提取，按简体中文术语标准化，并使用独立公开来源进行保守交叉核对。"
      }
    },
    {
      "locationId": "location-mapgenie-435717",
      "sourceLocationId": 435717,
      "categoryId": "category-12342-legendary-chest",
      "status": "unresolved",
      "confidence": 0.0,
      "summaryZhCN": "奖励尚未确认",
      "rewards": [],
      "sources": [],
      "conflicts": [],
      "review": {
        "state": "machine_checked",
        "lastReviewedAt": "2026-07-22T21:47:54.651231Z",
        "method": "atlas_reward_builder_v1",
        "reviewer": null,
        "changeReasonZhCN": "从地点原始奖励字段提取，按简体中文术语标准化，并使用独立公开来源进行保守交叉核对。"
      }
    },
    {
      "locationId": "location-mapgenie-435768",
      "sourceLocationId": 435768,
      "categoryId": "category-12342-legendary-chest",
      "status": "unresolved",
      "confidence": 0.0,
      "summaryZhCN": "奖励尚未确认",
      "rewards": [],
      "sources": [],
      "conflicts": [],
      "review": {
        "state": "machine_checked",
        "lastReviewedAt": "2026-07-22T21:47:54.651231Z",
        "method": "atlas_reward_builder_v1",
        "reviewer": null,
        "changeReasonZhCN": "从地点原始奖励字段提取，按简体中文术语标准化，并使用独立公开来源进行保守交叉核对。"
      }
    },
    {
      "locationId": "location-mapgenie-435774",
      "sourceLocationId": 435774,
      "categoryId": "category-12342-legendary-chest",
      "status": "unresolved",
      "confidence": 0.0,
      "summaryZhCN": "奖励尚未确认",
      "rewards": [],
      "sources": [],
      "conflicts": [],
      "review": {
        "state": "machine_checked",
        "lastReviewedAt": "2026-07-22T21:47:54.651231Z",
        "method": "atlas_reward_builder_v1",
        "reviewer": null,
        "changeReasonZhCN": "从地点原始奖励字段提取，按简体中文术语标准化，并使用独立公开来源进行保守交叉核对。"
      }
    },
    {
      "locationId": "location-mapgenie-435851",
      "sourceLocationId": 435851,
      "categoryId": "category-12342-legendary-chest",
      "status": "unresolved",
      "confidence": 0.0,
      "summaryZhCN": "奖励尚未确认",
      "rewards": [],
      "sources": [],
      "conflicts": [],
      "review": {
        "state": "machine_checked",
        "lastReviewedAt": "2026-07-22T21:47:54.651231Z",
        "method": "atlas_reward_builder_v1",
        "reviewer": null,
        "changeReasonZhCN": "从地点原始奖励字段提取，按简体中文术语标准化，并使用独立公开来源进行保守交叉核对。"
      }
    },
    {
      "locationId": "location-mapgenie-435852",
      "sourceLocationId": 435852,
      "categoryId": "category-12342-legendary-chest",
      "status": "unresolved",
      "confidence": 0.0,
      "summaryZhCN": "奖励尚未确认",
      "rewards": [],
      "sources": [],
      "conflicts": [],
      "review": {
        "state": "machine_checked",
        "lastReviewedAt": "2026-07-22T21:47:54.651231Z",
        "method": "atlas_reward_builder_v1",
        "reviewer": null,
        "changeReasonZhCN": "从地点原始奖励字段提取，按简体中文术语标准化，并使用独立公开来源进行保守交叉核对。"
      }
    },
    {
      "locationId": "location-mapgenie-435930",
      "sourceLocationId": 435930,
      "categoryId": "category-12342-legendary-chest",
      "status": "unresolved",
      "confidence": 0.0,
      "summaryZhCN": "奖励尚未确认",
      "rewards": [],
      "sources": [],
      "conflicts": [],
      "review": {
        "state": "machine_checked",
        "lastReviewedAt": "2026-07-22T21:47:54.651231Z",
        "method": "atlas_reward_builder_v1",
        "reviewer": null,
        "changeReasonZhCN": "从地点原始奖励字段提取，按简体中文术语标准化，并使用独立公开来源进行保守交叉核对。"
      }
    }
  ]
}
